r2x_core/__init__.py
r2x_core/datafile.py
r2x_core/exceptions.py
r2x_core/file_readers.py
r2x_core/file_types.py
r2x_core/getters.py
r2x_core/h5_readers.py
r2x_core/logger.py
r2x_core/plugin_base.py
r2x_core/plugin_config.py
r2x_core/plugin_context.py
r2x_core/plugin_expose.py
r2x_core/processors.py
r2x_core/py.typed
r2x_core/reader.py
r2x_core/result.py
r2x_core/rules.py
r2x_core/rules_executor.py
r2x_core/store.py
r2x_core/system.py
r2x_core/time_series.py
r2x_core/types.py
r2x_core/units/__init__.py
r2x_core/units/_mixins.py
r2x_core/units/_specs.py
r2x_core/units/_utils.py
r2x_core/units/py.typed
r2x_core/utils/__init__.py
r2x_core/utils/_component.py
r2x_core/utils/_datafile.py
r2x_core/utils/_rules.py
r2x_core/utils/_system.py
r2x_core/utils/_upgrader.py
r2x_core/utils/file_operations.py
r2x_core/utils/overrides.py
r2x_core/utils/parser.py
r2x_core/utils/validation.py
r2x_core/versioning.py
r2x_core-0.4.0.dist-info/WHEEL
r2x_core-0.4.0.dist-info/METADATA
r2x_core-0.4.0.dist-info/RECORD
