Metadata-Version: 2.3
Name: r2x-core
Version: 0.4.0
Summary: Extensible framework for building power system model translators with plugin architecture
Keywords: power-systems,energy-modeling,model-translation,reeds,plexos,switch,sienna,plugin-architecture
Author: pesap, kodiobika, Vivienne Liu, Micah Webb, Kinshuk Panda, mcllerena, jarry7
Author-email: pesap <pesap@users.noreply.github.com>, kodiobika <kodiobika@users.noreply.github.com>, Vivienne Liu <vivienne.liu@nrel.gov>, Micah Webb <micahpw@user.noreply.github.com>, Kinshuk Panda <7632244+k1nshuk@users.noreply.github.com>, mcllerena <mcllerena@users.noreply.github.com>, jarry7 <27745389+jarry7@users.noreply.github.com>
License: BSD 3-Clause License
Classifier: Development Status :: 5 - Production/Stable
Classifier: Intended Audience :: Developers
Classifier: Intended Audience :: Science/Research
Classifier: License :: OSI Approved :: BSD License
Classifier: Natural Language :: English
Classifier: Operating System :: OS Independent
Classifier: Programming Language :: Python :: 3.11
Classifier: Programming Language :: Python :: 3.12
Classifier: Programming Language :: Python :: 3.13
Classifier: Programming Language :: Python :: 3.14
Classifier: Topic :: File Formats :: JSON
Classifier: Topic :: Scientific/Engineering
Classifier: Topic :: Scientific/Engineering :: Information Analysis
Classifier: Topic :: Scientific/Engineering :: Interface Engine/Protocol Translator
Classifier: Topic :: Software Development :: Build Tools
Classifier: Topic :: Software Development :: Libraries :: Python Modules
Classifier: Typing :: Typed
Requires-Dist: h5py>=3.13.0,<4.0.0
Requires-Dist: infrasys>=1.0.0,<2.0.0
Requires-Dist: loguru>=0.7.3,<0.8.0
Requires-Dist: packaging>=24.0,<26.0
Requires-Dist: polars>=1.33.1,<2.0.0
Requires-Dist: pydantic>=2.11.9,<3.0.0
Requires-Dist: rust-ok>=0.2.2,<1.0.0
Maintainer: pesap, Kinshuk Panda, mcllerena, jarry7, kodiobika
Maintainer-email: pesap <pesap@users.noreply.github.com>, Kinshuk Panda <7632244+k1nshuk@users.noreply.github.com>, mcllerena <mcllerena@users.noreply.github.com>, jarry7 <27745389+jarry7@users.noreply.github.com>, kodiobika <kodiobika@users.noreply.github.com>
Requires-Python: >=3.11, <3.14
Project-URL: Changelog, https://nrel.github.io/r2x-core/CHANGELOG.html
Project-URL: Documentation, https://nrel.github.io/r2x-core/
Project-URL: Homepage, https://github.com/NREL/r2x-core
Project-URL: Issues, https://github.com/NREL/r2x-core/issues
Project-URL: Repository, https://github.com/NREL/r2x-core
